vdist/__init__.py
vdist/builder.py
vdist/buildmachine.py
vdist/configuration.py
vdist/console_parser.py
vdist/defaults.py
vdist/source.py
vdist/vdist_launcher.py
vdist/profiles/__init__.py
vdist/profiles/debian.sh
vdist/profiles/fedora.sh
vdist/profiles/internal_profiles.json
vdist-2.3.0.post9.data/data/share/man/manvdist/vdist.1
vdist-2.3.0.post9.dist-info/LICENSE.txt
vdist-2.3.0.post9.dist-info/METADATA
vdist-2.3.0.post9.dist-info/WHEEL
vdist-2.3.0.post9.dist-info/entry_points.txt
vdist-2.3.0.post9.dist-info/top_level.txt
vdist-2.3.0.post9.dist-info/RECORD
