Metadata-Version: 2.1
Name: vdist
Version: 2.3.0.post9
Summary: Create OS packages from Python projects using Docker containers
Home-page: https://github.com/dante-signal31/vdist
Author: objectified, dante-signal31
Author-email: objectified@gmail.com, dante.signal31@gmail.com
License: MIT
Keywords: python docker deployment packaging
Platform: UNKNOWN
Classifier: Development Status :: 3 - Alpha
Classifier: Environment :: Console
Classifier: Intended Audience :: Developers
Classifier: Operating System :: MacOS :: MacOS X
Classifier: Operating System :: Unix
Classifier: Operating System :: POSIX
Classifier: License :: OSI Approved :: MIT License
Classifier: Programming Language :: Python :: 3
Classifier: Programming Language :: Python :: 3.6
License-File: LICENSE.txt
Requires-Dist: docker (==6.0.1)
Requires-Dist: jinja2 (==3.1.2)
Requires-Dist: urllib3 (==1.26.14)
